{
  "project_info": {
    "project_number": "205661651618",
    "project_id": "inklusive-draw",
    "storage_bucket": "inklusive-draw.appspot.com"
  },
  "client": [
    {
      "client_info": {
        "mobilesdk_app_id": "1:205661651618:android:807b144e4e681973588dfb",
        "android_client_info": {
          "package_name": "com.fyp.inclusive_draw"
        }
      },
      "oauth_client": [
        {
          "client_id": "205661651618-jnemof26hmkcql43hd9kskdge7s4ugel.apps.googleusercontent.com",
          "client_type": 3
        }
      ],
      "api_key": [
        {
          "current_key": "AIzaSyAbll23IuyoS1YjBUwhfRtOLg3UB4RCfkU"
        }
      ],
      "services": {
        "appinvite_service": {
          "other_platform_oauth_client": [
            {
              "client_id": "205661651618-jnemof26hmkcql43hd9kskdge7s4ugel.apps.googleusercontent.com",
              "client_type": 3
            }
          ]
        }
      }
    }
  ],
  "configuration_version": "1"
}